{
	"credit": "Made with Blockbench",
	"texture_size": [128, 128],
	"textures": {
		"2": "optifine/cit/textures/displaycase",
		"particle": "./textures/displaycase"
	},
	"elements": [
		{
			"from": [-16, 0, 0],
			"to": [16, 16, 16],
			"faces": {
				"north": {"uv": [0, 0, 4, 2], "texture": "#2"},
				"east": {"uv": [0, 7.125, 2, 9.125], "texture": "#2"},
				"south": {"uv": [0, 2, 4, 4], "texture": "#2"},
				"west": {"uv": [2, 7.125, 4, 9.125], "texture": "#2"},
				"up": {"uv": [4, 6, 0, 4], "texture": "#2"},
				"down": {"uv": [8, 0, 4, 2], "texture": "#2"}
			}
		},
		{
			"from": [-15, 16, 15],
			"to": [15, 25, 16],
			"faces": {
				"north": {"uv": [0, 6, 3.75, 7.125], "texture": "#2"},
				"east": {"uv": [6.625, 8.25, 6.75, 9.375], "texture": "#2"},
				"south": {"uv": [3.75, 6, 7.5, 7.125], "texture": "#2"},
				"west": {"uv": [6.75, 8.25, 6.875, 9.375], "texture": "#2"},
				"up": {"uv": [11.5, 5.5, 7.75, 5.375], "texture": "#2"},
				"down": {"uv": [11.5, 5.5, 7.75, 5.625], "texture": "#2"}
			}
		},
		{
			"from": [-16, 24, 14],
			"to": [16, 26, 16.1],
			"faces": {
				"north": {"uv": [7.75, 3.125, 11.75, 3.375], "texture": "#2"},
				"east": {"uv": [8, 1.75, 8.25, 2], "texture": "#2"},
				"south": {"uv": [7.75, 3.375, 11.75, 3.625], "texture": "#2"},
				"west": {"uv": [8.25, 1.75, 8.5, 2], "texture": "#2"},
				"up": {"uv": [11.75, 3.875, 7.75, 3.625], "texture": "#2"},
				"down": {"uv": [11.75, 3.875, 7.75, 4.125], "texture": "#2"}
			}
		},
		{
			"from": [14.999, 18, -1],
			"to": [16.019, 19, 17.001],
			"rotation": {"angle": -22.5, "axis": "x", "origin": [-15.5, 18.5, 0.5]},
			"faces": {
				"north": {"uv": [8.375, 7.125, 8.5, 7.25], "texture": "#2"},
				"east": {"uv": [7.75, 5.875, 10, 6], "texture": "#2"},
				"south": {"uv": [8.375, 7.25, 8.5, 7.375], "texture": "#2"},
				"west": {"uv": [8, 0, 10.25, 0.125], "texture": "#2"},
				"up": {"uv": [4.625, 10.5, 4.5, 8.25], "texture": "#2"},
				"down": {"uv": [4.75, 8.25, 4.625, 10.5], "texture": "#2"}
			}
		},
		{
			"from": [-16, 18, -1],
			"to": [-14.98, 19, 17.001],
			"rotation": {"angle": -22.5, "axis": "x", "origin": [-15.5, 18.5, 0.5]},
			"faces": {
				"north": {"uv": [8.375, 7.375, 8.5, 7.5], "texture": "#2"},
				"east": {"uv": [8, 0.125, 10.25, 0.25], "texture": "#2"},
				"south": {"uv": [7.5, 8.375, 7.625, 8.5], "texture": "#2"},
				"west": {"uv": [8, 0.25, 10.25, 0.375], "texture": "#2"},
				"up": {"uv": [4.875, 10.5, 4.75, 8.25], "texture": "#2"},
				"down": {"uv": [5, 8.25, 4.875, 10.5], "texture": "#2"}
			}
		},
		{
			"from": [15, 0, -1],
			"to": [16, 18, 0],
			"faces": {
				"north": {"uv": [7.75, 7.125, 7.875, 9.375], "texture": "#2"},
				"east": {"uv": [7.875, 7.125, 8, 9.375], "texture": "#2"},
				"south": {"uv": [8, 7.125, 8.125, 9.375], "texture": "#2"},
				"west": {"uv": [8.125, 7.125, 8.25, 9.375], "texture": "#2"},
				"up": {"uv": [8.375, 8.375, 8.25, 8.25], "texture": "#2"},
				"down": {"uv": [8.5, 0.625, 8.375, 0.75], "texture": "#2"}
			}
		},
		{
			"from": [15, 16, 15],
			"to": [16, 25, 16],
			"faces": {
				"north": {"uv": [8, 0.625, 8.125, 1.75], "texture": "#2"},
				"east": {"uv": [8.125, 0.625, 8.25, 1.75], "texture": "#2"},
				"south": {"uv": [8.25, 0.625, 8.375, 1.75], "texture": "#2"},
				"west": {"uv": [6, 8.25, 6.125, 9.375], "texture": "#2"},
				"up": {"uv": [8.5, 1.375, 8.375, 1.25], "texture": "#2"},
				"down": {"uv": [8.5, 1.375, 8.375, 1.5], "texture": "#2"}
			}
		},
		{
			"from": [-16, 16, 15],
			"to": [-15, 25, 16],
			"faces": {
				"north": {"uv": [6.125, 8.25, 6.25, 9.375], "texture": "#2"},
				"east": {"uv": [6.25, 8.25, 6.375, 9.375], "texture": "#2"},
				"south": {"uv": [6.375, 8.25, 6.5, 9.375], "texture": "#2"},
				"west": {"uv": [6.5, 8.25, 6.625, 9.375], "texture": "#2"},
				"up": {"uv": [8.5, 1.625, 8.375, 1.5], "texture": "#2"},
				"down": {"uv": [8.5, 1.625, 8.375, 1.75], "texture": "#2"}
			}
		},
		{
			"from": [-16, 0, -1],
			"to": [-15, 18, 0],
			"faces": {
				"north": {"uv": [4, 8.25, 4.125, 10.5], "texture": "#2"},
				"east": {"uv": [4.125, 8.25, 4.25, 10.5], "texture": "#2"},
				"south": {"uv": [4.25, 8.25, 4.375, 10.5], "texture": "#2"},
				"west": {"uv": [4.375, 8.25, 4.5, 10.5], "texture": "#2"},
				"up": {"uv": [8.5, 0.875, 8.375, 0.75], "texture": "#2"},
				"down": {"uv": [8.5, 0.875, 8.375, 1], "texture": "#2"}
			}
		},
		{
			"from": [-15, 0, -1],
			"to": [15, 1, 0],
			"faces": {
				"north": {"uv": [7.75, 4.625, 11.5, 4.75], "texture": "#2"},
				"east": {"uv": [8.375, 1, 8.5, 1.125], "texture": "#2"},
				"south": {"uv": [7.75, 4.75, 11.5, 4.875], "texture": "#2"},
				"west": {"uv": [8.375, 1.125, 8.5, 1.25], "texture": "#2"},
				"up": {"uv": [11.5, 5, 7.75, 4.875], "texture": "#2"},
				"down": {"uv": [11.5, 5, 7.75, 5.125], "texture": "#2"}
			}
		},
		{
			"from": [-15, 15, -1],
			"to": [15, 17, 0],
			"faces": {
				"north": {"uv": [7.75, 4.125, 11.5, 4.375], "texture": "#2"},
				"east": {"uv": [7.25, 8.25, 7.375, 8.5], "texture": "#2"},
				"south": {"uv": [7.75, 4.375, 11.5, 4.625], "texture": "#2"},
				"west": {"uv": [7.375, 8.25, 7.5, 8.5], "texture": "#2"},
				"up": {"uv": [11.5, 5.25, 7.75, 5.125], "texture": "#2"},
				"down": {"uv": [11.5, 5.25, 7.75, 5.375], "texture": "#2"}
			}
		},
		{
			"from": [-1, 1, -1],
			"to": [1, 15, 0],
			"faces": {
				"north": {"uv": [5.5, 8.25, 5.625, 10], "texture": "#2"},
				"east": {"uv": [5.625, 8.25, 5.75, 10], "texture": "#2"},
				"south": {"uv": [5.75, 8.25, 5.875, 10], "texture": "#2"},
				"west": {"uv": [5.875, 8.25, 6, 10], "texture": "#2"},
				"up": {"uv": [7.625, 8.375, 7.5, 8.25], "texture": "#2"},
				"down": {"uv": [7.75, 8.25, 7.625, 8.375], "texture": "#2"}
			}
		},
		{
			"from": [-15, 17, 0],
			"to": [15, 18, 16],
			"rotation": {"angle": -22.5, "axis": "x", "origin": [0.5, 17.5, 0.5]},
			"faces": {
				"north": {"uv": [7.75, 5.625, 11.5, 5.75], "texture": "#2"},
				"east": {"uv": [8, 0.375, 10, 0.5], "texture": "#2"},
				"south": {"uv": [7.75, 5.75, 11.5, 5.875], "texture": "#2"},
				"west": {"uv": [8, 0.5, 10, 0.625], "texture": "#2"},
				"up": {"uv": [7.75, 4, 4, 2], "texture": "#2"},
				"down": {"uv": [7.75, 4, 4, 6], "texture": "#2"}
			}
		},
		{
			"from": [15, 16, 0],
			"to": [16, 25, 15],
			"faces": {
				"north": {"uv": [7.125, 8.25, 7.25, 9.375], "texture": "#2"},
				"east": {"uv": [7.5, 6, 9.375, 7.125], "texture": "#2"},
				"south": {"uv": [8.25, 7.125, 8.375, 8.25], "texture": "#2"},
				"west": {"uv": [7.75, 2, 9.625, 3.125], "texture": "#2"},
				"up": {"uv": [5.375, 10.125, 5.25, 8.25], "texture": "#2"},
				"down": {"uv": [5.5, 8.25, 5.375, 10.125], "texture": "#2"}
			}
		},
		{
			"from": [-15.999, 16, 0],
			"to": [-15, 25, 15],
			"faces": {
				"north": {"uv": [6.875, 8.25, 7, 9.375], "texture": "#2"},
				"east": {"uv": [4, 7.125, 5.875, 8.25], "texture": "#2"},
				"south": {"uv": [7, 8.25, 7.125, 9.375], "texture": "#2"},
				"west": {"uv": [5.875, 7.125, 7.75, 8.25], "texture": "#2"},
				"up": {"uv": [5.125, 10.125, 5, 8.25], "texture": "#2"},
				"down": {"uv": [5.25, 8.25, 5.125, 10.125], "texture": "#2"}
			}
		}
	],
	"display": {
		"thirdperson_righthand": {
			"rotation": [-21, -32, -16],
			"translation": [-1, -0.25, -2.75],
			"scale": [0.3, 0.3, 0.3]
		},
		"thirdperson_lefthand": {
			"rotation": [-21, -32, -16],
			"translation": [-1, -0.25, -2.75],
			"scale": [0.3, 0.3, 0.3]
		},
		"firstperson_righthand": {
			"translation": [0.5, -1, 0],
			"scale": [0.3, 0.3, 0.3]
		},
		"firstperson_lefthand": {
			"translation": [-4.25, -1, 0],
			"scale": [0.3, 0.3, 0.3]
		},
		"ground": {
			"scale": [0.3, 0.3, 0.3]
		},
		"gui": {
			"rotation": [0, 136, 10],
			"translation": [-2, -1.75, 0],
			"scale": [0.45, 0.45, 0.45]
		},
		"head": {
			"translation": [12, -19, 0],
			"scale": [1.5, 1.5, 1.5]
		},
		"fixed": {
			"rotation": [-90, 0, 0],
			"translation": [0, 0, -15],
			"scale": [2.01, 2.01, 2.01]
		}
	},
	"groups": [
		0,
		1,
		{
			"name": "edges",
			"origin": [0, 0, 0],
			"color": 0,
			"children": [2, 3, 4, 5, 6, 7, 8, 9, 10, 11]
		},
		{
			"name": "glass",
			"origin": [8, 8, 8],
			"color": 0,
			"children": [12, 13, 14]
		}
	]
}